paifulogger/__init__.py
paifulogger/__main__.py
paifulogger/log.py
paifulogger/localizations/en.json
paifulogger/localizations/ja.json
paifulogger/localizations/zh.json
paifulogger/localizations/zh_tw.json
paifulogger/src/Paifu.py
paifulogger/src/__init__.py
paifulogger/src/get_paifu.py
paifulogger/src/get_place.py
paifulogger/src/local.py
paifulogger/src/log_into_html.py
paifulogger/src/log_into_xlsx.py
paifulogger/src/url_log.py
paifulogger/src/url_request_handler.py
Tenhou_Paifu_Logger-0.3.2.dist-info/LICENSE
Tenhou_Paifu_Logger-0.3.2.dist-info/METADATA
Tenhou_Paifu_Logger-0.3.2.dist-info/WHEEL
Tenhou_Paifu_Logger-0.3.2.dist-info/entry_points.txt
Tenhou_Paifu_Logger-0.3.2.dist-info/top_level.txt
Tenhou_Paifu_Logger-0.3.2.dist-info/RECORD
