Metadata-Version: 2.1
Name: Tenhou-Paifu-Logger
Version: 0.3.2
Summary: Logging tenhou paifu into excel or html file with some key information.
Author-email: Jim137 <jim@mail.jim137.eu.org>
License: MIT License
Project-URL: Homepage, https://github.com/Jim137/Tenhou-Paifu-Logger
Keywords: mahjong,review,logger,paifu,tenhou,haifu,paipu,riichi-mahjong
Classifier: License :: OSI Approved :: MIT License
Classifier: Programming Language :: Python
Classifier: Programming Language :: Python :: 3
Requires-Python: >=3.9
License-File: LICENSE
Requires-Dist: openpyxl
Requires-Dist: lxml
Requires-Dist: tables
Requires-Dist: pandas
